local_qwen3b_part015/__init__.py
local_qwen3b_part015/qwen2.5-3b-instruct-q5_k_m.gguf.part_015
local_qwen3b_part015-0.0.1.dist-info/METADATA
local_qwen3b_part015-0.0.1.dist-info/WHEEL
local_qwen3b_part015-0.0.1.dist-info/top_level.txt
local_qwen3b_part015-0.0.1.dist-info/RECORD
